[
  {
    "trend_arrow": "FLAT", 
    "display_time": "2017-02-17T23:42:27-08:00", 
    "noise": 1, 
    "system_time": "2017-02-18T06:33:31-08:00", 
    "direction": "Flat", 
    "sgv": 103, 
    "dateString": "2017-02-17T23:42:27-08:00", 
    "date": 1487403747000, 
    "unfiltered": 119776, 
    "filtered": 117632, 
    "device": "openaps://indy-ex2/cgm", 
    "rssi": 186, 
    "type": "sgv", 
    "glucose": 103
  }, 
  {
    "trend_arrow": "FLAT", 
    "display_time": "2017-02-17T23:37:27-08:00", 
    "noise": 1, 
    "system_time": "2017-02-18T06:28:31-08:00", 
    "direction": "Flat", 
    "sgv": 102, 
    "dateString": "2017-02-17T23:37:27-08:00", 
    "date": 1487403447000, 
    "unfiltered": 118256, 
    "filtered": 119728, 
    "device": "openaps://indy-ex2/cgm", 
    "rssi": 190, 
    "type": "sgv", 
    "glucose": 102
  }
]