[
  {
    "trend_arrow": "FLAT", 
    "display_time": "2017-01-04T18:49:41-08:00", 
    "noise": 1, 
    "system_time": "2017-01-05T01:41:36-08:00", 
    "direction": "Flat", 
    "sgv": 113, 
    "dateString": "2017-01-04T18:49:41-08:00", 
    "date": 1483584581000, 
    "unfiltered": 122288, 
    "filtered": 123072, 
    "device": "openaps://indy-ex2/cgm", 
    "rssi": 185, 
    "type": "sgv", 
    "glucose": 113
  }, 
  {
    "trend_arrow": "FLAT", 
    "display_time": "2017-01-04T18:44:41-08:00", 
    "noise": 1, 
    "system_time": "2017-01-05T01:36:37-08:00", 
    "direction": "Flat", 
    "sgv": 113, 
    "dateString": "2017-01-04T18:44:41-08:00", 
    "date": 1483584281000, 
    "unfiltered": 122320, 
    "filtered": 123840, 
    "device": "openaps://indy-ex2/cgm", 
    "rssi": 442, 
    "type": "sgv", 
    "glucose": 113
  }
]