[
  {
    "trend_arrow": "FLAT", 
    "display_time": "2016-12-28T06:45:04-08:00", 
    "noise": 1, 
    "system_time": "2016-12-28T13:37:09-08:00", 
    "direction": "Flat", 
    "sgv": 105, 
    "dateString": "2016-12-28T06:45:04-08:00", 
    "date": 1482936304000, 
    "unfiltered": 119200, 
    "filtered": 124896, 
    "device": "openaps://indy-ex2/cgm", 
    "rssi": 952, 
    "type": "sgv", 
    "glucose": 105
  }, 
  {
    "trend_arrow": "FLAT", 
    "display_time": "2016-12-28T06:40:03-08:00", 
    "noise": 1, 
    "system_time": "2016-12-28T13:32:07-08:00", 
    "direction": "Flat", 
    "sgv": 110, 
    "dateString": "2016-12-28T06:40:03-08:00", 
    "date": 1482936003000, 
    "unfiltered": 123328, 
    "filtered": 127904, 
    "device": "openaps://indy-ex2/cgm", 
    "rssi": 177, 
    "type": "sgv", 
    "glucose": 110
  }
]