[
  {
    "trend_arrow": "FLAT", 
    "display_time": "2017-02-11T13:12:54-08:00", 
    "noise": 1, 
    "system_time": "2017-02-11T20:03:59-08:00", 
    "direction": "Flat", 
    "sgv": 93, 
    "dateString": "2017-02-11T13:12:54-08:00", 
    "device": "openaps://indy-ex2/cgm", 
    "unfiltered": 107952, 
    "rssi": 445, 
    "date": 1486847574000, 
    "filtered": 104768, 
    "type": "sgv", 
    "glucose": 93
  }, 
  {
    "trend_arrow": "FLAT", 
    "display_time": "2017-02-11T13:07:53-08:00", 
    "noise": 1, 
    "system_time": "2017-02-11T19:58:58-08:00", 
    "direction": "Flat", 
    "sgv": 91, 
    "dateString": "2017-02-11T13:07:53-08:00", 
    "date": 1486847273000, 
    "unfiltered": 105648, 
    "filtered": 104384, 
    "device": "openaps://indy-ex2/cgm", 
    "rssi": 198, 
    "type": "sgv", 
    "glucose": 91
  }, 
  {
    "trend_arrow": "45_UP", 
    "display_time": "2017-02-11T13:27:54-08:00", 
    "noise": 1, 
    "system_time": "2017-02-11T20:18:58-08:00", 
    "direction": "FortyFiveUp", 
    "sgv": 110, 
    "dateString": "2017-02-11T13:27:54-08:00", 
    "date": 1486848474000, 
    "unfiltered": 123120, 
    "filtered": 114096, 
    "device": "openaps://indy-ex2/cgm", 
    "rssi": 197, 
    "type": "sgv", 
    "glucose": 110
  }, 
  {
    "trend_arrow": "FLAT", 
    "display_time": "2017-02-11T13:22:53-08:00", 
    "noise": 1, 
    "system_time": "2017-02-11T20:13:58-08:00", 
    "direction": "Flat", 
    "sgv": 104, 
    "dateString": "2017-02-11T13:22:53-08:00", 
    "device": "openaps://indy-ex2/cgm", 
    "unfiltered": 117376, 
    "rssi": 196, 
    "date": 1486848173000, 
    "filtered": 109616, 
    "type": "sgv", 
    "glucose": 104
  }, 
  {
    "trend_arrow": "45_UP", 
    "display_time": "2017-02-11T13:42:54-08:00", 
    "noise": 1, 
    "system_time": "2017-02-11T20:33:58-08:00", 
    "direction": "FortyFiveUp", 
    "sgv": 126, 
    "dateString": "2017-02-11T13:42:54-08:00", 
    "date": 1486849374000, 
    "unfiltered": 137920, 
    "filtered": 130688, 
    "device": "openaps://indy-ex2/cgm", 
    "rssi": 192, 
    "type": "sgv", 
    "glucose": 126
  }, 
  {
    "trend_arrow": "45_UP", 
    "display_time": "2017-02-11T13:37:53-08:00", 
    "noise": 1, 
    "system_time": "2017-02-11T20:28:58-08:00", 
    "direction": "FortyFiveUp", 
    "sgv": 120, 
    "dateString": "2017-02-11T13:37:53-08:00", 
    "device": "openaps://indy-ex2/cgm", 
    "unfiltered": 132704, 
    "rssi": 192, 
    "date": 1486849073000, 
    "filtered": 125312, 
    "type": "sgv", 
    "glucose": 120
  }, 
  {
    "trend_arrow": "SINGLE_UP", 
    "display_time": "2017-02-11T14:12:54-08:00", 
    "noise": 1, 
    "system_time": "2017-02-11T21:03:58-08:00", 
    "direction": "SingleUp", 
    "sgv": 160, 
    "dateString": "2017-02-11T14:12:54-08:00", 
    "date": 1486851174000, 
    "unfiltered": 168672, 
    "filtered": 152192, 
    "device": "openaps://indy-ex2/cgm", 
    "rssi": 468, 
    "type": "sgv", 
    "glucose": 160
  }, 
  {
    "trend_arrow": "45_UP", 
    "display_time": "2017-02-11T14:07:53-08:00", 
    "noise": 1, 
    "system_time": "2017-02-11T20:58:58-08:00", 
    "direction": "FortyFiveUp", 
    "sgv": 152, 
    "dateString": "2017-02-11T14:07:53-08:00", 
    "device": "openaps://indy-ex2/cgm", 
    "unfiltered": 161664, 
    "rssi": 188, 
    "date": 1486850873000, 
    "filtered": 143360, 
    "type": "sgv", 
    "glucose": 152
  }, 
  {
    "trend_arrow": "FLAT", 
    "display_time": "2017-02-11T21:12:53-08:00", 
    "noise": 1, 
    "system_time": "2017-02-12T04:03:57-08:00", 
    "direction": "Flat", 
    "sgv": 186, 
    "dateString": "2017-02-11T21:12:53-08:00", 
    "device": "openaps://indy-ex2/cgm", 
    "unfiltered": 192864, 
    "rssi": 443, 
    "date": 1486876373000, 
    "filtered": 194400, 
    "type": "sgv", 
    "glucose": 186
  }, 
  {
    "trend_arrow": "45_UP", 
    "display_time": "2017-02-11T21:07:52-08:00", 
    "noise": 1, 
    "system_time": "2017-02-12T03:58:57-08:00", 
    "direction": "FortyFiveUp", 
    "sgv": 191, 
    "dateString": "2017-02-11T21:07:52-08:00", 
    "device": "openaps://indy-ex2/cgm", 
    "unfiltered": 197312, 
    "rssi": 185, 
    "date": 1486876072000, 
    "filtered": 188992, 
    "type": "sgv", 
    "glucose": 191
  }
]