[
  {
    "trend_arrow": "FLAT", 
    "display_time": "2016-12-21T02:39:22-08:00", 
    "noise": 1, 
    "system_time": "2016-12-21T10:38:44-08:00", 
    "direction": "Flat", 
    "sgv": 129, 
    "dateString": "2016-12-21T02:39:22-08:00", 
    "date": 1482316762000, 
    "unfiltered": 141600, 
    "filtered": 146720, 
    "device": "openaps://indy-ex2/cgm", 
    "rssi": 180, 
    "type": "sgv", 
    "glucose": 129
  }, 
  {
    "trend_arrow": "FLAT", 
    "display_time": "2016-12-21T02:34:22-08:00", 
    "noise": 1, 
    "system_time": "2016-12-21T10:33:45-08:00", 
    "direction": "Flat", 
    "sgv": 134, 
    "dateString": "2016-12-21T02:34:22-08:00", 
    "date": 1482316462000, 
    "unfiltered": 145344, 
    "filtered": 147584, 
    "device": "openaps://indy-ex2/cgm", 
    "rssi": 191, 
    "type": "sgv", 
    "glucose": 134
  }
]