[
  {
    "trend_arrow": "FLAT", 
    "display_time": "2016-12-29T06:24:59-08:00", 
    "noise": 1, 
    "system_time": "2016-12-29T13:17:03-08:00", 
    "direction": "Flat", 
    "sgv": 148, 
    "dateString": "2016-12-29T06:24:59-08:00", 
    "date": 1483021499000, 
    "unfiltered": 154496, 
    "filtered": 154432, 
    "device": "openaps://indy-ex2/cgm", 
    "rssi": 179, 
    "type": "sgv", 
    "glucose": 148
  }, 
  {
    "trend_arrow": "FLAT", 
    "display_time": "2016-12-29T06:19:59-08:00", 
    "noise": 1, 
    "system_time": "2016-12-29T13:12:03-08:00", 
    "direction": "Flat", 
    "sgv": 148, 
    "dateString": "2016-12-29T06:19:59-08:00", 
    "date": 1483021199000, 
    "unfiltered": 154400, 
    "filtered": 152992, 
    "device": "openaps://indy-ex2/cgm", 
    "rssi": 180, 
    "type": "sgv", 
    "glucose": 148
  }
]