[
  {
    "trend_arrow": "FLAT", 
    "display_time": "2017-01-07T03:48:27-08:00", 
    "noise": 1, 
    "system_time": "2017-01-07T10:40:23-08:00", 
    "direction": "Flat", 
    "sgv": 64, 
    "dateString": "2017-01-07T03:48:27-08:00", 
    "date": 1483789707000, 
    "unfiltered": 74272, 
    "filtered": 71328, 
    "device": "openaps://indy-ex2/cgm", 
    "rssi": 197, 
    "type": "sgv", 
    "glucose": 64
  }, 
  {
    "trend_arrow": "FLAT", 
    "display_time": "2017-01-07T03:43:27-08:00", 
    "noise": 1, 
    "system_time": "2017-01-07T10:35:23-08:00", 
    "direction": "Flat", 
    "sgv": 59, 
    "dateString": "2017-01-07T03:43:27-08:00", 
    "date": 1483789407000, 
    "unfiltered": 70096, 
    "filtered": 71088, 
    "device": "openaps://indy-ex2/cgm", 
    "rssi": 192, 
    "type": "sgv", 
    "glucose": 59
  }
]