[
  {
    "trend_arrow": "FLAT", 
    "display_time": "2017-01-21T06:43:31-08:00", 
    "noise": 1, 
    "system_time": "2017-01-21T13:35:27-08:00", 
    "direction": "Flat", 
    "sgv": 130, 
    "dateString": "2017-01-21T06:43:31-08:00", 
    "date": 1485009811000, 
    "unfiltered": 127584, 
    "filtered": 126800, 
    "device": "openaps://indy-ex2/cgm", 
    "rssi": 191, 
    "type": "sgv", 
    "glucose": 130
  }, 
  {
    "trend_arrow": "FLAT", 
    "display_time": "2017-01-21T06:38:31-08:00", 
    "noise": 1, 
    "system_time": "2017-01-21T13:30:27-08:00", 
    "direction": "Flat", 
    "sgv": 129, 
    "dateString": "2017-01-21T06:38:31-08:00", 
    "date": 1485009511000, 
    "unfiltered": 126400, 
    "filtered": 126400, 
    "device": "openaps://indy-ex2/cgm", 
    "rssi": 192, 
    "type": "sgv", 
    "glucose": 129
  }
]