[
  {
    "trend_arrow": "45_UP", 
    "display_time": "2017-03-06T07:36:57-08:00", 
    "noise": 1, 
    "system_time": "2017-03-06T14:27:23-08:00", 
    "direction": "FortyFiveUp", 
    "sgv": 103, 
    "dateString": "2017-03-06T07:36:57-08:00", 
    "device": "openaps://indy-ex2/cgm", 
    "unfiltered": 111408, 
    "rssi": 193, 
    "date": 1488814617000, 
    "filtered": 94800, 
    "type": "sgv", 
    "glucose": 103
  }, 
  {
    "trend_arrow": "FLAT", 
    "display_time": "2017-03-06T07:31:57-08:00", 
    "noise": 1, 
    "system_time": "2017-03-06T14:22:23-08:00", 
    "direction": "Flat", 
    "sgv": 91, 
    "dateString": "2017-03-06T07:31:57-08:00", 
    "device": "openaps://indy-ex2/cgm", 
    "unfiltered": 99792, 
    "rssi": 169, 
    "date": 1488814317000, 
    "filtered": 89968, 
    "type": "sgv", 
    "glucose": 91
  }
]