[
  {
    "trend_arrow": "45_DOWN", 
    "display_time": "2016-12-31T21:49:57-08:00", 
    "noise": 1, 
    "system_time": "2017-01-01T04:41:52-08:00", 
    "direction": "FortyFiveDown", 
    "sgv": 159, 
    "dateString": "2016-12-31T21:49:57-08:00", 
    "date": 1483249797000, 
    "unfiltered": 201088, 
    "filtered": 219872, 
    "device": "openaps://indy-ex2/cgm", 
    "rssi": 193, 
    "type": "sgv", 
    "glucose": 159
  }, 
  {
    "trend_arrow": "45_DOWN", 
    "display_time": "2016-12-31T21:44:57-08:00", 
    "noise": 1, 
    "system_time": "2017-01-01T04:36:52-08:00", 
    "direction": "FortyFiveDown", 
    "sgv": 171, 
    "dateString": "2016-12-31T21:44:57-08:00", 
    "date": 1483249497000, 
    "unfiltered": 213408, 
    "filtered": 228672, 
    "device": "openaps://indy-ex2/cgm", 
    "rssi": 187, 
    "type": "sgv", 
    "glucose": 171
  }
]