[
  {
    "trend_arrow": "FLAT", 
    "display_time": "2017-01-30T06:12:32-08:00", 
    "noise": 1, 
    "system_time": "2017-01-30T13:03:53-08:00", 
    "direction": "Flat", 
    "sgv": 82, 
    "dateString": "2017-01-30T06:12:32-08:00", 
    "date": 1485785552000, 
    "unfiltered": 94544, 
    "filtered": 97792, 
    "device": "openaps://indy-ex2/cgm", 
    "rssi": 194, 
    "type": "sgv", 
    "glucose": 82
  }, 
  {
    "trend_arrow": "FLAT", 
    "display_time": "2017-01-30T06:07:32-08:00", 
    "noise": 1, 
    "system_time": "2017-01-30T12:58:53-08:00", 
    "direction": "Flat", 
    "sgv": 85, 
    "dateString": "2017-01-30T06:07:32-08:00", 
    "date": 1485785252000, 
    "unfiltered": 96848, 
    "filtered": 100736, 
    "device": "openaps://indy-ex2/cgm", 
    "rssi": 194, 
    "type": "sgv", 
    "glucose": 85
  }
]