[
  {
    "trend_arrow": "FLAT", 
    "display_time": "2017-01-23T20:28:55-08:00", 
    "noise": 1, 
    "system_time": "2017-01-24T03:20:16-08:00", 
    "direction": "Flat", 
    "sgv": 183, 
    "dateString": "2017-01-23T20:28:55-08:00", 
    "date": 1485232135000, 
    "unfiltered": 198944, 
    "filtered": 204064, 
    "device": "openaps://indy-ex2/cgm", 
    "rssi": 197, 
    "type": "sgv", 
    "glucose": 183
  }, 
  {
    "trend_arrow": "45_DOWN", 
    "display_time": "2017-01-23T20:23:54-08:00", 
    "noise": 1, 
    "system_time": "2017-01-24T03:15:16-08:00", 
    "direction": "FortyFiveDown", 
    "sgv": 184, 
    "dateString": "2017-01-23T20:23:54-08:00", 
    "date": 1485231834000, 
    "unfiltered": 200320, 
    "filtered": 209600, 
    "device": "openaps://indy-ex2/cgm", 
    "rssi": 197, 
    "type": "sgv", 
    "glucose": 184
  }
]