[
  {
    "trend_arrow": "FLAT", 
    "display_time": "2016-12-31T07:59:59-08:00", 
    "noise": 1, 
    "system_time": "2016-12-31T14:51:55-08:00", 
    "direction": "Flat", 
    "sgv": 97, 
    "dateString": "2016-12-31T07:59:59-08:00", 
    "device": "openaps://indy-ex2/cgm", 
    "unfiltered": 138272, 
    "rssi": 178, 
    "date": 1483199999000, 
    "filtered": 137472, 
    "type": "sgv", 
    "glucose": 97
  }, 
  {
    "trend_arrow": "FLAT", 
    "display_time": "2016-12-31T07:54:59-08:00", 
    "noise": 1, 
    "system_time": "2016-12-31T14:46:55-08:00", 
    "direction": "Flat", 
    "sgv": 99, 
    "dateString": "2016-12-31T07:54:59-08:00", 
    "device": "openaps://indy-ex2/cgm", 
    "unfiltered": 139712, 
    "rssi": 179, 
    "date": 1483199699000, 
    "filtered": 137216, 
    "type": "sgv", 
    "glucose": 99
  }
]