[
  {
    "trend_arrow": "45_UP", 
    "display_time": "2016-12-28T13:25:02-08:00", 
    "noise": 1, 
    "system_time": "2016-12-28T20:17:06-08:00", 
    "direction": "FortyFiveUp", 
    "sgv": 178, 
    "dateString": "2016-12-28T13:25:02-08:00", 
    "device": "openaps://indy-ex2/cgm", 
    "unfiltered": 179296, 
    "rssi": 179, 
    "date": 1482960302000, 
    "filtered": 168608, 
    "type": "sgv", 
    "glucose": 178
  }, 
  {
    "trend_arrow": "45_UP", 
    "display_time": "2016-12-28T13:20:02-08:00", 
    "noise": 1, 
    "system_time": "2016-12-28T20:12:06-08:00", 
    "direction": "FortyFiveUp", 
    "sgv": 171, 
    "dateString": "2016-12-28T13:20:02-08:00", 
    "device": "openaps://indy-ex2/cgm", 
    "unfiltered": 173888, 
    "rssi": 181, 
    "date": 1482960002000, 
    "filtered": 160352, 
    "type": "sgv", 
    "glucose": 171
  }
]