[
  {
    "trend_arrow": "NOT_COMPUTABLE", 
    "display_time": "2017-01-14T07:42:59-08:00", 
    "noise": 1, 
    "system_time": "2017-01-14T14:34:55-08:00", 
    "direction": "NOT COMPUTABLE", 
    "sgv": 116, 
    "dateString": "2017-01-14T07:42:59-08:00", 
    "device": "openaps://indy-ex2/cgm", 
    "unfiltered": 130640, 
    "rssi": 176, 
    "date": 1484408579000, 
    "filtered": 128592, 
    "type": "sgv", 
    "glucose": 116
  }, 
  {
    "trend_arrow": "FLAT", 
    "display_time": "2017-01-14T07:23:00-08:00", 
    "noise": 1, 
    "system_time": "2017-01-14T14:14:55-08:00", 
    "direction": "Flat", 
    "sgv": 112, 
    "dateString": "2017-01-14T07:23:00-08:00", 
    "device": "openaps://indy-ex2/cgm", 
    "unfiltered": 127392, 
    "rssi": 192, 
    "date": 1484407380000, 
    "filtered": 121824, 
    "type": "sgv", 
    "glucose": 112
  }
]