[
  {
    "trend_arrow": "45_DOWN", 
    "display_time": "2017-03-06T18:01:55-08:00", 
    "noise": 1, 
    "direction": "FortyFiveDown", 
    "system_time": "2017-03-07T00:52:21-08:00", 
    "sgv": 73, 
    "dateString": "2017-03-06T18:01:55-08:00", 
    "device": "openaps://indy-ex2/cgm", 
    "unfiltered": 82448, 
    "rssi": 185, 
    "date": 1488852115000.0, 
    "filtered": 90848, 
    "type": "sgv", 
    "glucose": 73
  }, 
  {
    "trend_arrow": "45_DOWN", 
    "display_time": "2017-03-06T17:51:55-08:00", 
    "noise": 1, 
    "direction": "FortyFiveDown", 
    "system_time": "2017-03-07T00:42:21-08:00", 
    "sgv": 85, 
    "dateString": "2017-03-06T17:51:55-08:00", 
    "device": "openaps://indy-ex2/cgm", 
    "unfiltered": 93936, 
    "rssi": 165, 
    "date": 1488851515000.0, 
    "filtered": 102240, 
    "type": "sgv", 
    "glucose": 85
  }, 
  {
    "trend_arrow": "FLAT", 
    "display_time": "2017-03-06T17:46:55-08:00", 
    "noise": 1, 
    "direction": "Flat", 
    "system_time": "2017-03-07T00:37:21-08:00", 
    "sgv": 90, 
    "dateString": "2017-03-06T17:46:55-08:00", 
    "device": "openaps://indy-ex2/cgm", 
    "unfiltered": 98752, 
    "rssi": 166, 
    "date": 1488851215000.0, 
    "filtered": 107792, 
    "type": "sgv", 
    "glucose": 90
  }, 
  {
    "trend_arrow": "FLAT", 
    "display_time": "2017-03-06T17:41:55-08:00", 
    "noise": 1, 
    "direction": "Flat", 
    "system_time": "2017-03-07T00:32:21-08:00", 
    "sgv": 97, 
    "dateString": "2017-03-06T17:41:55-08:00", 
    "device": "openaps://indy-ex2/cgm", 
    "unfiltered": 105536, 
    "rssi": 190, 
    "date": 1488850915000.0, 
    "filtered": 112672, 
    "type": "sgv", 
    "glucose": 97
  }
]