[
  {
    "trend_arrow": "45_UP", 
    "display_time": "2017-01-15T17:52:54-08:00", 
    "noise": 1, 
    "system_time": "2017-01-16T00:44:49-08:00", 
    "direction": "FortyFiveUp", 
    "sgv": 109, 
    "dateString": "2017-01-15T17:52:54-08:00", 
    "device": "openaps://indy-ex2/cgm", 
    "unfiltered": 123184, 
    "rssi": 197, 
    "date": 1484531574000, 
    "filtered": 116720, 
    "type": "sgv", 
    "glucose": 109
  }, 
  {
    "trend_arrow": "45_UP", 
    "display_time": "2017-01-15T17:47:54-08:00", 
    "noise": 1, 
    "system_time": "2017-01-16T00:39:50-08:00", 
    "direction": "FortyFiveUp", 
    "sgv": 105, 
    "dateString": "2017-01-15T17:47:54-08:00", 
    "device": "openaps://indy-ex2/cgm", 
    "unfiltered": 120288, 
    "rssi": 216, 
    "date": 1484531274000, 
    "filtered": 111840, 
    "type": "sgv", 
    "glucose": 105
  }
]