[
  {
    "trend_arrow": "FLAT", 
    "display_time": "2016-12-26T21:40:08-08:00", 
    "noise": 1, 
    "system_time": "2016-12-27T04:32:13-08:00", 
    "direction": "Flat", 
    "sgv": 178, 
    "dateString": "2016-12-26T21:40:08-08:00", 
    "device": "openaps://indy-ex2/cgm", 
    "unfiltered": 193408, 
    "rssi": 194, 
    "date": 1482817208000, 
    "filtered": 196448, 
    "type": "sgv", 
    "glucose": 178
  }, 
  {
    "trend_arrow": "FLAT", 
    "display_time": "2016-12-26T21:35:08-08:00", 
    "noise": 1, 
    "system_time": "2016-12-27T04:27:13-08:00", 
    "direction": "Flat", 
    "sgv": 181, 
    "dateString": "2016-12-26T21:35:08-08:00", 
    "device": "openaps://indy-ex2/cgm", 
    "unfiltered": 195616, 
    "rssi": 203, 
    "date": 1482816908000, 
    "filtered": 196384, 
    "type": "sgv", 
    "glucose": 181
  }
]