[
  {
    "trend_arrow": "FLAT", 
    "display_time": "2017-01-08T23:28:20-08:00", 
    "noise": 1, 
    "system_time": "2017-01-09T06:20:16-08:00", 
    "direction": "Flat", 
    "sgv": 87, 
    "dateString": "2017-01-08T23:28:20-08:00", 
    "device": "openaps://indy-ex2/cgm", 
    "unfiltered": 93168, 
    "rssi": 191, 
    "date": 1483946900000, 
    "filtered": 89648, 
    "type": "sgv", 
    "glucose": 87
  }, 
  {
    "trend_arrow": "FLAT", 
    "display_time": "2017-01-08T23:23:20-08:00", 
    "noise": 1, 
    "system_time": "2017-01-09T06:15:16-08:00", 
    "direction": "Flat", 
    "sgv": 84, 
    "dateString": "2017-01-08T23:23:20-08:00", 
    "device": "openaps://indy-ex2/cgm", 
    "unfiltered": 91152, 
    "rssi": 190, 
    "date": 1483946600000, 
    "filtered": 87536, 
    "type": "sgv", 
    "glucose": 84
  }
]