[
  {
    "trend_arrow": "FLAT", 
    "display_time": "2016-12-25T01:10:16-08:00", 
    "noise": 1, 
    "direction": "Flat", 
    "system_time": "2016-12-25T08:02:21-08:00", 
    "sgv": 243, 
    "dateString": "2016-12-25T01:10:16-08:00", 
    "device": "openaps://indy-ex2/cgm", 
    "unfiltered": 239872, 
    "rssi": 185, 
    "date": 1482657016000.0, 
    "filtered": 242880, 
    "type": "sgv", 
    "glucose": 243
  }, 
  {
    "trend_arrow": "FLAT", 
    "display_time": "2016-12-25T01:05:16-08:00", 
    "noise": 1, 
    "direction": "Flat", 
    "system_time": "2016-12-25T07:57:20-08:00", 
    "sgv": 244, 
    "dateString": "2016-12-25T01:05:16-08:00", 
    "device": "openaps://indy-ex2/cgm", 
    "unfiltered": 240480, 
    "rssi": 186, 
    "date": 1482656716000.0, 
    "filtered": 244128, 
    "type": "sgv", 
    "glucose": 244
  }, 
  {
    "trend_arrow": "FLAT", 
    "display_time": "2016-12-25T01:00:16-08:00", 
    "noise": 1, 
    "direction": "Flat", 
    "system_time": "2016-12-25T07:52:20-08:00", 
    "sgv": 248, 
    "dateString": "2016-12-25T01:00:16-08:00", 
    "device": "openaps://indy-ex2/cgm", 
    "unfiltered": 244000, 
    "rssi": 196, 
    "date": 1482656416000.0, 
    "filtered": 244704, 
    "type": "sgv", 
    "glucose": 248
  }, 
  {
    "trend_arrow": "FLAT", 
    "display_time": "2016-12-25T00:55:16-08:00", 
    "noise": 1, 
    "direction": "Flat", 
    "system_time": "2016-12-25T07:47:20-08:00", 
    "sgv": 250, 
    "dateString": "2016-12-25T00:55:16-08:00", 
    "device": "openaps://indy-ex2/cgm", 
    "unfiltered": 245632, 
    "rssi": 191, 
    "date": 1482656116000.0, 
    "filtered": 245600, 
    "type": "sgv", 
    "glucose": 250
  }, 
  {
    "trend_arrow": "FLAT", 
    "display_time": "2016-12-25T00:50:16-08:00", 
    "noise": 1, 
    "direction": "Flat", 
    "system_time": "2016-12-25T07:42:20-08:00", 
    "sgv": 251, 
    "dateString": "2016-12-25T00:50:16-08:00", 
    "device": "openaps://indy-ex2/cgm", 
    "unfiltered": 245696, 
    "rssi": 187, 
    "date": 1482655816000.0, 
    "filtered": 247648, 
    "type": "sgv", 
    "glucose": 251
  }, 
  {
    "trend_arrow": "FLAT", 
    "display_time": "2016-12-25T00:45:16-08:00", 
    "noise": 1, 
    "direction": "Flat", 
    "system_time": "2016-12-25T07:37:20-08:00", 
    "sgv": 251, 
    "dateString": "2016-12-25T00:45:16-08:00", 
    "device": "openaps://indy-ex2/cgm", 
    "unfiltered": 245888, 
    "rssi": 185, 
    "date": 1482655516000.0, 
    "filtered": 250624, 
    "type": "sgv", 
    "glucose": 251
  }
]