[
  {
    "trend_arrow": "FLAT", 
    "system_time": "2017-01-15T09:24:52", 
    "noise": 1, 
    "direction": "Flat", 
    "sgv": 90, 
    "display_time": "2017-01-15T02:32:57", 
    "date": 1484476377000.0, 
    "dateString": "2017-01-15T02:32:57", 
    "unfiltered": 109040, 
    "filtered": 107072, 
    "device": "openaps://indy-ex2/cgm", 
    "rssi": 173, 
    "type": "sgv", 
    "glucose": 90
  }, 
  {
    "trend_arrow": "FLAT", 
    "system_time": "2017-01-15T09:19:52", 
    "noise": 1, 
    "direction": "Flat", 
    "sgv": 88, 
    "display_time": "2017-01-15T02:27:57", 
    "date": 1484476077000.0, 
    "dateString": "2017-01-15T02:27:57", 
    "unfiltered": 107776, 
    "filtered": 106144, 
    "device": "openaps://indy-ex2/cgm", 
    "rssi": 174, 
    "type": "sgv", 
    "glucose": 88
  }, 
  {
    "trend_arrow": "FLAT", 
    "system_time": "2017-01-15T09:14:52", 
    "noise": 1, 
    "direction": "Flat", 
    "sgv": 87, 
    "display_time": "2017-01-15T02:22:57", 
    "date": 1484475777000.0, 
    "dateString": "2017-01-15T02:22:57", 
    "unfiltered": 106880, 
    "filtered": 105648, 
    "device": "openaps://indy-ex2/cgm", 
    "rssi": 193, 
    "type": "sgv", 
    "glucose": 87
  }, 
  {
    "trend_arrow": "FLAT", 
    "system_time": "2017-01-15T09:09:52", 
    "noise": 1, 
    "direction": "Flat", 
    "sgv": 86, 
    "display_time": "2017-01-15T02:17:57", 
    "date": 1484475477000.0, 
    "dateString": "2017-01-15T02:17:57", 
    "unfiltered": 105920, 
    "filtered": 105392, 
    "device": "openaps://indy-ex2/cgm", 
    "rssi": 195, 
    "type": "sgv", 
    "glucose": 86
  }, 
  {
    "trend_arrow": "FLAT", 
    "system_time": "2017-01-15T09:04:52", 
    "noise": 1, 
    "direction": "Flat", 
    "sgv": 85, 
    "display_time": "2017-01-15T02:12:57", 
    "date": 1484475177000.0, 
    "dateString": "2017-01-15T02:12:57", 
    "unfiltered": 104896, 
    "filtered": 104912, 
    "device": "openaps://indy-ex2/cgm", 
    "rssi": 195, 
    "type": "sgv", 
    "glucose": 85
  }, 
  {
    "trend_arrow": "FLAT", 
    "system_time": "2017-01-15T08:59:52", 
    "noise": 1, 
    "direction": "Flat", 
    "sgv": 85, 
    "display_time": "2017-01-15T02:07:57", 
    "date": 1484474877000.0, 
    "dateString": "2017-01-15T02:07:57", 
    "unfiltered": 105152, 
    "filtered": 103728, 
    "device": "openaps://indy-ex2/cgm", 
    "rssi": 193, 
    "type": "sgv", 
    "glucose": 85
  }
]