[
  {
    "trend_arrow": "FLAT", 
    "display_time": "2017-02-01T21:12:22-08:00", 
    "noise": 1, 
    "system_time": "2017-02-02T04:03:43-08:00", 
    "direction": "Flat", 
    "sgv": 90, 
    "dateString": "2017-02-01T21:12:22-08:00", 
    "device": "openaps://indy-ex2/cgm", 
    "unfiltered": 101728, 
    "rssi": 187, 
    "date": 1486012342000, 
    "filtered": 99376, 
    "type": "sgv", 
    "glucose": 90
  }, 
  {
    "trend_arrow": "FLAT", 
    "display_time": "2017-02-01T21:07:22-08:00", 
    "noise": 1, 
    "system_time": "2017-02-02T03:58:43-08:00", 
    "direction": "Flat", 
    "sgv": 87, 
    "dateString": "2017-02-01T21:07:22-08:00", 
    "device": "openaps://indy-ex2/cgm", 
    "unfiltered": 99328, 
    "rssi": 197, 
    "date": 1486012042000, 
    "filtered": 98576, 
    "type": "sgv", 
    "glucose": 87
  }
]