[
  {
    "trend_arrow": "FLAT", 
    "system_time": "2017-01-29T14:43:56", 
    "noise": 1, 
    "direction": "Flat", 
    "sgv": 96, 
    "display_time": "2017-01-29T07:52:36", 
    "date": 1485705156000.0, 
    "dateString": "2017-01-29T07:52:36", 
    "unfiltered": 102496, 
    "filtered": 105376, 
    "device": "openaps://indy-ex2/cgm", 
    "rssi": 196, 
    "type": "sgv", 
    "glucose": 96
  }, 
  {
    "trend_arrow": "FLAT", 
    "system_time": "2017-01-29T14:38:56", 
    "noise": 1, 
    "direction": "Flat", 
    "sgv": 98, 
    "display_time": "2017-01-29T07:47:36", 
    "date": 1485704856000.0, 
    "dateString": "2017-01-29T07:47:36", 
    "unfiltered": 104096, 
    "filtered": 107616, 
    "device": "openaps://indy-ex2/cgm", 
    "rssi": 197, 
    "type": "sgv", 
    "glucose": 98
  }, 
  {
    "trend_arrow": "FLAT", 
    "system_time": "2017-01-29T14:33:56", 
    "noise": 1, 
    "direction": "Flat", 
    "sgv": 100, 
    "display_time": "2017-01-29T07:42:36", 
    "date": 1485704556000.0, 
    "dateString": "2017-01-29T07:42:36", 
    "unfiltered": 106128, 
    "filtered": 109760, 
    "device": "openaps://indy-ex2/cgm", 
    "rssi": 196, 
    "type": "sgv", 
    "glucose": 100
  }, 
  {
    "trend_arrow": "FLAT", 
    "system_time": "2017-01-29T14:28:57", 
    "noise": 1, 
    "direction": "Flat", 
    "sgv": 103, 
    "display_time": "2017-01-29T07:37:36", 
    "date": 1485704256000.0, 
    "dateString": "2017-01-29T07:37:36", 
    "unfiltered": 108656, 
    "filtered": 111680, 
    "device": "openaps://indy-ex2/cgm", 
    "rssi": 196, 
    "type": "sgv", 
    "glucose": 103
  }, 
  {
    "trend_arrow": "FLAT", 
    "system_time": "2017-01-29T14:23:56", 
    "noise": 1, 
    "direction": "Flat", 
    "sgv": 106, 
    "display_time": "2017-01-29T07:32:36", 
    "date": 1485703956000.0, 
    "dateString": "2017-01-29T07:32:36", 
    "unfiltered": 110944, 
    "filtered": 113568, 
    "device": "openaps://indy-ex2/cgm", 
    "rssi": 197, 
    "type": "sgv", 
    "glucose": 106
  }, 
  {
    "trend_arrow": "FLAT", 
    "system_time": "2017-01-29T14:18:56", 
    "noise": 1, 
    "direction": "Flat", 
    "sgv": 108, 
    "display_time": "2017-01-29T07:27:36", 
    "date": 1485703656000.0, 
    "dateString": "2017-01-29T07:27:36", 
    "unfiltered": 112624, 
    "filtered": 115824, 
    "device": "openaps://indy-ex2/cgm", 
    "rssi": 197, 
    "type": "sgv", 
    "glucose": 108
  }
]