[
  {
    "trend_arrow": "FLAT", 
    "display_time": "2016-12-30T04:35:04-08:00", 
    "noise": 1, 
    "system_time": "2016-12-30T11:26:59-08:00", 
    "direction": "Flat", 
    "sgv": 118, 
    "dateString": "2016-12-30T04:35:04-08:00", 
    "device": "openaps://indy-ex2/cgm", 
    "unfiltered": 164960, 
    "rssi": 192, 
    "date": 1483101304000, 
    "filtered": 166784, 
    "type": "sgv", 
    "glucose": 118
  }, 
  {
    "trend_arrow": "FLAT", 
    "display_time": "2016-12-30T04:30:04-08:00", 
    "noise": 1, 
    "system_time": "2016-12-30T11:22:00-08:00", 
    "direction": "Flat", 
    "sgv": 119, 
    "dateString": "2016-12-30T04:30:04-08:00", 
    "device": "openaps://indy-ex2/cgm", 
    "unfiltered": 166336, 
    "rssi": 193, 
    "date": 1483101004000, 
    "filtered": 167712, 
    "type": "sgv", 
    "glucose": 119
  }
]