[
  {
    "trend_arrow": "FLAT", 
    "system_time": "2017-01-03T13:46:43", 
    "noise": 1, 
    "direction": "Flat", 
    "sgv": 102, 
    "display_time": "2017-01-03T06:54:47", 
    "date": 1483455287000.0, 
    "dateString": "2017-01-03T06:54:47", 
    "unfiltered": 114960, 
    "filtered": 116384, 
    "device": "openaps://indy-ex2/cgm", 
    "rssi": 195, 
    "type": "sgv", 
    "glucose": 102
  }, 
  {
    "trend_arrow": "FLAT", 
    "system_time": "2017-01-03T13:41:43", 
    "noise": 1, 
    "direction": "Flat", 
    "sgv": 109, 
    "display_time": "2017-01-03T06:49:47", 
    "date": 1483454987000.0, 
    "dateString": "2017-01-03T06:49:47", 
    "unfiltered": 115680, 
    "filtered": 113728, 
    "device": "openaps://indy-ex2/cgm", 
    "rssi": 187, 
    "type": "sgv", 
    "glucose": 109
  }, 
  {
    "trend_arrow": "FLAT", 
    "system_time": "2017-01-03T13:36:42", 
    "noise": 1, 
    "direction": "Flat", 
    "sgv": 110, 
    "display_time": "2017-01-03T06:44:47", 
    "date": 1483454687000.0, 
    "dateString": "2017-01-03T06:44:47", 
    "unfiltered": 116320, 
    "filtered": 110192, 
    "device": "openaps://indy-ex2/cgm", 
    "rssi": 176, 
    "type": "sgv", 
    "glucose": 110
  }, 
  {
    "trend_arrow": "FLAT", 
    "system_time": "2017-01-03T13:31:43", 
    "noise": 1, 
    "direction": "Flat", 
    "sgv": 108, 
    "display_time": "2017-01-03T06:39:47", 
    "date": 1483454387000.0, 
    "dateString": "2017-01-03T06:39:47", 
    "unfiltered": 115088, 
    "filtered": 108496, 
    "device": "openaps://indy-ex2/cgm", 
    "rssi": 190, 
    "type": "sgv", 
    "glucose": 108
  }, 
  {
    "trend_arrow": "FLAT", 
    "system_time": "2017-01-03T13:26:43", 
    "noise": 1, 
    "direction": "Flat", 
    "sgv": 103, 
    "display_time": "2017-01-03T06:34:47", 
    "date": 1483454087000.0, 
    "dateString": "2017-01-03T06:34:47", 
    "unfiltered": 110032, 
    "filtered": 109760, 
    "device": "openaps://indy-ex2/cgm", 
    "rssi": 190, 
    "type": "sgv", 
    "glucose": 103
  }, 
  {
    "trend_arrow": "FLAT", 
    "system_time": "2017-01-03T13:21:43", 
    "noise": 1, 
    "direction": "Flat", 
    "sgv": 98, 
    "display_time": "2017-01-03T06:29:47", 
    "date": 1483453787000.0, 
    "dateString": "2017-01-03T06:29:47", 
    "unfiltered": 105664, 
    "filtered": 113040, 
    "device": "openaps://indy-ex2/cgm", 
    "rssi": 190, 
    "type": "sgv", 
    "glucose": 98
  }
]