[
  {
    "trend_arrow": "FLAT", 
    "display_time": "2017-01-25T23:27:49-08:00", 
    "noise": 1, 
    "system_time": "2017-01-26T06:19:09-08:00", 
    "direction": "Flat", 
    "sgv": 69, 
    "dateString": "2017-01-25T23:27:49-08:00", 
    "device": "openaps://indy-ex2/cgm", 
    "unfiltered": 92784, 
    "rssi": 178, 
    "date": 1485415669000, 
    "filtered": 94128, 
    "type": "sgv", 
    "glucose": 69
  }, 
  {
    "trend_arrow": "FLAT", 
    "display_time": "2017-01-25T23:22:49-08:00", 
    "noise": 1, 
    "system_time": "2017-01-26T06:14:10-08:00", 
    "direction": "Flat", 
    "sgv": 70, 
    "dateString": "2017-01-25T23:22:49-08:00", 
    "device": "openaps://indy-ex2/cgm", 
    "unfiltered": 93632, 
    "rssi": 445, 
    "date": 1485415369000, 
    "filtered": 95744, 
    "type": "sgv", 
    "glucose": 70
  }
]