[
  {
    "trend_arrow": "FLAT", 
    "display_time": "2017-02-08T17:23:05-08:00", 
    "noise": 1, 
    "system_time": "2017-02-09T00:14:10-08:00", 
    "direction": "Flat", 
    "sgv": 100, 
    "dateString": "2017-02-08T17:23:05-08:00", 
    "device": "openaps://indy-ex2/cgm", 
    "unfiltered": 114256, 
    "rssi": 179, 
    "date": 1486603385000, 
    "filtered": 110368, 
    "type": "sgv", 
    "glucose": 100
  }, 
  {
    "trend_arrow": "FLAT", 
    "display_time": "2017-02-08T17:18:06-08:00", 
    "noise": 1, 
    "system_time": "2017-02-09T00:09:10-08:00", 
    "direction": "Flat", 
    "sgv": 97, 
    "dateString": "2017-02-08T17:18:06-08:00", 
    "device": "openaps://indy-ex2/cgm", 
    "unfiltered": 111824, 
    "rssi": 429, 
    "date": 1486603086000, 
    "filtered": 108048, 
    "type": "sgv", 
    "glucose": 97
  }
]