[
  {
    "trend_arrow": "45_UP", 
    "system_time": "2017-01-07T11:20:23", 
    "noise": 1, 
    "direction": "FortyFiveUp", 
    "sgv": 81, 
    "display_time": "2017-01-07T04:28:27", 
    "date": 1483792107000.0, 
    "dateString": "2017-01-07T04:28:27", 
    "unfiltered": 88768, 
    "filtered": 80512, 
    "device": "openaps://indy-ex2/cgm", 
    "rssi": 200, 
    "type": "sgv", 
    "glucose": 81
  }, 
  {
    "trend_arrow": "45_UP", 
    "system_time": "2017-01-07T11:15:23", 
    "noise": 1, 
    "direction": "FortyFiveUp", 
    "sgv": 77, 
    "display_time": "2017-01-07T04:23:27", 
    "date": 1483791807000.0, 
    "dateString": "2017-01-07T04:23:27", 
    "unfiltered": 84992, 
    "filtered": 75440, 
    "device": "openaps://indy-ex2/cgm", 
    "rssi": 200, 
    "type": "sgv", 
    "glucose": 77
  }, 
  {
    "trend_arrow": "FLAT", 
    "system_time": "2017-01-07T11:10:23", 
    "noise": 1, 
    "direction": "Flat", 
    "sgv": 70, 
    "display_time": "2017-01-07T04:18:27", 
    "date": 1483791507000.0, 
    "dateString": "2017-01-07T04:18:27", 
    "unfiltered": 79840, 
    "filtered": 72304, 
    "device": "openaps://indy-ex2/cgm", 
    "rssi": 200, 
    "type": "sgv", 
    "glucose": 70
  }, 
  {
    "trend_arrow": "FLAT", 
    "system_time": "2017-01-07T11:05:23", 
    "noise": 1, 
    "direction": "Flat", 
    "sgv": 61, 
    "display_time": "2017-01-07T04:13:27", 
    "date": 1483791207000.0, 
    "dateString": "2017-01-07T04:13:27", 
    "unfiltered": 72000, 
    "filtered": 71328, 
    "device": "openaps://indy-ex2/cgm", 
    "rssi": 194, 
    "type": "sgv", 
    "glucose": 61
  }, 
  {
    "trend_arrow": "FLAT", 
    "system_time": "2017-01-07T11:00:23", 
    "noise": 1, 
    "direction": "Flat", 
    "sgv": 60, 
    "display_time": "2017-01-07T04:08:27", 
    "date": 1483790907000.0, 
    "dateString": "2017-01-07T04:08:27", 
    "unfiltered": 71600, 
    "filtered": 71728, 
    "device": "openaps://indy-ex2/cgm", 
    "rssi": 191, 
    "type": "sgv", 
    "glucose": 60
  }, 
  {
    "trend_arrow": "FLAT", 
    "system_time": "2017-01-07T10:55:23", 
    "noise": 1, 
    "direction": "Flat", 
    "sgv": 60, 
    "display_time": "2017-01-07T04:03:27", 
    "date": 1483790607000.0, 
    "dateString": "2017-01-07T04:03:27", 
    "unfiltered": 71424, 
    "filtered": 72208, 
    "device": "openaps://indy-ex2/cgm", 
    "rssi": 194, 
    "type": "sgv", 
    "glucose": 60
  }
]