[
  {
    "trend_arrow": "FLAT", 
    "system_time": "2017-01-02T20:06:46", 
    "noise": 1, 
    "direction": "Flat", 
    "sgv": 128, 
    "display_time": "2017-01-02T13:14:50", 
    "date": 1483391690000.0, 
    "dateString": "2017-01-02T13:14:50", 
    "unfiltered": 152032, 
    "filtered": 153376, 
    "device": "openaps://indy-ex2/cgm", 
    "rssi": 190, 
    "type": "sgv", 
    "glucose": 128
  }, 
  {
    "trend_arrow": "FLAT", 
    "system_time": "2017-01-02T20:01:46", 
    "noise": 1, 
    "direction": "Flat", 
    "sgv": 129, 
    "display_time": "2017-01-02T13:09:51", 
    "date": 1483391391000.0, 
    "dateString": "2017-01-02T13:09:51", 
    "unfiltered": 153056, 
    "filtered": 153536, 
    "device": "openaps://indy-ex2/cgm", 
    "rssi": 455, 
    "type": "sgv", 
    "glucose": 129
  }, 
  {
    "trend_arrow": "FLAT", 
    "system_time": "2017-01-02T19:56:46", 
    "noise": 1, 
    "direction": "Flat", 
    "sgv": 129, 
    "display_time": "2017-01-02T13:04:50", 
    "date": 1483391090000.0, 
    "dateString": "2017-01-02T13:04:50", 
    "unfiltered": 153216, 
    "filtered": 152544, 
    "device": "openaps://indy-ex2/cgm", 
    "rssi": 202, 
    "type": "sgv", 
    "glucose": 129
  }, 
  {
    "trend_arrow": "FLAT", 
    "system_time": "2017-01-02T19:51:46", 
    "noise": 1, 
    "direction": "Flat", 
    "sgv": 129, 
    "display_time": "2017-01-02T12:59:50", 
    "date": 1483390790000.0, 
    "dateString": "2017-01-02T12:59:50", 
    "unfiltered": 152736, 
    "filtered": 149920, 
    "device": "openaps://indy-ex2/cgm", 
    "rssi": 220, 
    "type": "sgv", 
    "glucose": 129
  }, 
  {
    "trend_arrow": "FLAT", 
    "system_time": "2017-01-02T19:46:46", 
    "noise": 1, 
    "direction": "Flat", 
    "sgv": 128, 
    "display_time": "2017-01-02T12:54:50", 
    "date": 1483390490000.0, 
    "dateString": "2017-01-02T12:54:50", 
    "unfiltered": 151648, 
    "filtered": 145888, 
    "device": "openaps://indy-ex2/cgm", 
    "rssi": 212, 
    "type": "sgv", 
    "glucose": 128
  }, 
  {
    "trend_arrow": "FLAT", 
    "system_time": "2017-01-02T19:41:46", 
    "noise": 1, 
    "direction": "Flat", 
    "sgv": 125, 
    "display_time": "2017-01-02T12:49:50", 
    "date": 1483390190000.0, 
    "dateString": "2017-01-02T12:49:50", 
    "unfiltered": 148960, 
    "filtered": 141408, 
    "device": "openaps://indy-ex2/cgm", 
    "rssi": 201, 
    "type": "sgv", 
    "glucose": 125
  }
]