[
  {
    "trend_arrow": "FLAT", 
    "display_time": "2017-01-14T07:08:00-08:00", 
    "noise": 1, 
    "system_time": "2017-01-14T13:59:55-08:00", 
    "direction": "Flat", 
    "sgv": 107, 
    "dateString": "2017-01-14T07:08:00-08:00", 
    "device": "openaps://indy-ex2/cgm", 
    "unfiltered": 123664, 
    "rssi": 190, 
    "date": 1484406480000, 
    "filtered": 126112, 
    "type": "sgv", 
    "glucose": 107
  }, 
  {
    "trend_arrow": "FLAT", 
    "display_time": "2017-01-14T07:03:00-08:00", 
    "noise": 1, 
    "system_time": "2017-01-14T13:54:55-08:00", 
    "direction": "Flat", 
    "sgv": 108, 
    "dateString": "2017-01-14T07:03:00-08:00", 
    "device": "openaps://indy-ex2/cgm", 
    "unfiltered": 124576, 
    "rssi": 192, 
    "date": 1484406180000, 
    "filtered": 126944, 
    "type": "sgv", 
    "glucose": 108
  }
]