[
  {
    "trend_arrow": "45_UP", 
    "display_time": "2017-01-19T22:53:37-08:00", 
    "noise": 1, 
    "system_time": "2017-01-20T05:45:32-08:00", 
    "direction": "FortyFiveUp", 
    "sgv": 203, 
    "dateString": "2017-01-19T22:53:37-08:00", 
    "device": "openaps://indy-ex2/cgm", 
    "unfiltered": 157280, 
    "rssi": 185, 
    "date": 1484895217000, 
    "filtered": 152640, 
    "type": "sgv", 
    "glucose": 203
  }, 
  {
    "trend_arrow": "SINGLE_UP", 
    "display_time": "2017-01-19T22:48:37-08:00", 
    "noise": 1, 
    "system_time": "2017-01-20T05:40:32-08:00", 
    "direction": "SingleUp", 
    "sgv": 202, 
    "dateString": "2017-01-19T22:48:37-08:00", 
    "device": "openaps://indy-ex2/cgm", 
    "unfiltered": 156928, 
    "rssi": 194, 
    "date": 1484894917000, 
    "filtered": 145088, 
    "type": "sgv", 
    "glucose": 202
  }
]