[
  {
    "trend_arrow": "FLAT", 
    "display_time": "2017-02-13T21:17:44-08:00", 
    "noise": 1, 
    "system_time": "2017-02-14T04:08:48-08:00", 
    "direction": "Flat", 
    "sgv": 113, 
    "dateString": "2017-02-13T21:17:44-08:00", 
    "device": "openaps://indy-ex2/cgm", 
    "unfiltered": 137472, 
    "rssi": 182, 
    "date": 1487049464000, 
    "filtered": 132576, 
    "type": "sgv", 
    "glucose": 113
  }, 
  {
    "trend_arrow": "45_UP", 
    "display_time": "2017-02-13T21:12:44-08:00", 
    "noise": 1, 
    "system_time": "2017-02-14T04:03:48-08:00", 
    "direction": "FortyFiveUp", 
    "sgv": 113, 
    "dateString": "2017-02-13T21:12:44-08:00", 
    "device": "openaps://indy-ex2/cgm", 
    "unfiltered": 137184, 
    "rssi": 185, 
    "date": 1487049164000, 
    "filtered": 128000, 
    "type": "sgv", 
    "glucose": 113
  }
]