[
  {
    "trend_arrow": "FLAT", 
    "display_time": "2017-03-05T03:17:01-08:00", 
    "noise": 1, 
    "system_time": "2017-03-05T10:07:28-08:00", 
    "direction": "Flat", 
    "sgv": 142, 
    "dateString": "2017-03-05T03:17:01-08:00", 
    "device": "openaps://indy-ex2/cgm", 
    "unfiltered": 167936, 
    "rssi": 185, 
    "date": 1488712621000, 
    "filtered": 163840, 
    "type": "sgv", 
    "glucose": 142
  }, 
  {
    "trend_arrow": "FLAT", 
    "display_time": "2017-03-05T03:12:02-08:00", 
    "noise": 1, 
    "system_time": "2017-03-05T10:02:28-08:00", 
    "direction": "Flat", 
    "sgv": 142, 
    "dateString": "2017-03-05T03:12:02-08:00", 
    "device": "openaps://indy-ex2/cgm", 
    "unfiltered": 168480, 
    "rssi": 185, 
    "date": 1488712322000, 
    "filtered": 162400, 
    "type": "sgv", 
    "glucose": 142
  }
]