[
  {
    "trend_arrow": "45_UP", 
    "display_time": "2017-03-05T13:07:00-08:00", 
    "noise": 1, 
    "system_time": "2017-03-05T19:57:26-08:00", 
    "direction": "FortyFiveUp", 
    "sgv": 123, 
    "dateString": "2017-03-05T13:07:00-08:00", 
    "device": "openaps://indy-ex2/cgm", 
    "unfiltered": 135936, 
    "rssi": 196, 
    "date": 1488748020000, 
    "filtered": 130528, 
    "type": "sgv", 
    "glucose": 123
  }, 
  {
    "trend_arrow": "45_UP", 
    "display_time": "2017-03-05T13:02:00-08:00", 
    "noise": 1, 
    "system_time": "2017-03-05T19:52:26-08:00", 
    "direction": "FortyFiveUp", 
    "sgv": 123, 
    "dateString": "2017-03-05T13:02:00-08:00", 
    "device": "openaps://indy-ex2/cgm", 
    "unfiltered": 135776, 
    "rssi": 187, 
    "date": 1488747720000, 
    "filtered": 123472, 
    "type": "sgv", 
    "glucose": 123
  }
]