[
  {
    "trend_arrow": "NOT_COMPUTABLE", 
    "system_time": "2017-03-06T04:12:25", 
    "noise": 3, 
    "direction": "NOT COMPUTABLE", 
    "sgv": 128, 
    "display_time": "2017-03-05T21:21:58", 
    "date": 1488777718000.0, 
    "dateString": "2017-03-05T21:21:58", 
    "unfiltered": 126016, 
    "filtered": 145568, 
    "device": "openaps://indy-ex2/cgm", 
    "rssi": 185, 
    "type": "sgv", 
    "glucose": 128
  }, 
  {
    "trend_arrow": "NOT_COMPUTABLE", 
    "system_time": "2017-03-06T04:07:25", 
    "noise": 3, 
    "direction": "NOT COMPUTABLE", 
    "sgv": 138, 
    "display_time": "2017-03-05T21:16:58", 
    "date": 1488777418000.0, 
    "dateString": "2017-03-05T21:16:58", 
    "unfiltered": 132288, 
    "filtered": 154976, 
    "device": "openaps://indy-ex2/cgm", 
    "rssi": 177, 
    "type": "sgv", 
    "glucose": 138
  }, 
  {
    "trend_arrow": "NOT_COMPUTABLE", 
    "system_time": "2017-03-06T04:02:25", 
    "noise": 3, 
    "direction": "NOT COMPUTABLE", 
    "sgv": 138, 
    "display_time": "2017-03-05T21:11:58", 
    "date": 1488777118000.0, 
    "dateString": "2017-03-05T21:11:58", 
    "unfiltered": 143904, 
    "filtered": 154720, 
    "device": "openaps://indy-ex2/cgm", 
    "rssi": 167, 
    "type": "sgv", 
    "glucose": 138
  }, 
  {
    "trend_arrow": "45_UP", 
    "system_time": "2017-03-06T03:57:25", 
    "noise": 2, 
    "direction": "FortyFiveUp", 
    "sgv": 130, 
    "display_time": "2017-03-05T21:06:58", 
    "date": 1488776818000.0, 
    "dateString": "2017-03-05T21:06:58", 
    "unfiltered": 159904, 
    "filtered": 146944, 
    "device": "openaps://indy-ex2/cgm", 
    "rssi": 175, 
    "type": "sgv", 
    "glucose": 130
  }, 
  {
    "trend_arrow": "SINGLE_UP", 
    "system_time": "2017-03-06T03:52:25", 
    "noise": 1, 
    "direction": "SingleUp", 
    "sgv": 146, 
    "display_time": "2017-03-05T21:01:58", 
    "date": 1488776518000.0, 
    "dateString": "2017-03-05T21:01:58", 
    "unfiltered": 162592, 
    "filtered": 137664, 
    "device": "openaps://indy-ex2/cgm", 
    "rssi": 185, 
    "type": "sgv", 
    "glucose": 146
  }, 
  {
    "trend_arrow": "FLAT", 
    "system_time": "2017-03-06T03:47:25", 
    "noise": 1, 
    "direction": "Flat", 
    "sgv": 120, 
    "display_time": "2017-03-05T20:56:59", 
    "date": 1488776219000.0, 
    "dateString": "2017-03-05T20:56:59", 
    "unfiltered": 137472, 
    "filtered": 131424, 
    "device": "openaps://indy-ex2/cgm", 
    "rssi": 185, 
    "type": "sgv", 
    "glucose": 120
  }
]