[
  {
    "trend_arrow": "FLAT", 
    "display_time": "2017-01-30T06:27:32-08:00", 
    "noise": 1, 
    "direction": "Flat", 
    "system_time": "2017-01-30T13:18:53-08:00", 
    "sgv": 90, 
    "dateString": "2017-01-30T06:27:32-08:00", 
    "device": "openaps://indy-ex2/cgm", 
    "unfiltered": 101616, 
    "rssi": 186, 
    "date": 1485786452000.0, 
    "filtered": 94064, 
    "type": "sgv", 
    "glucose": 90
  }, 
  {
    "trend_arrow": "FLAT", 
    "display_time": "2017-01-30T06:22:32-08:00", 
    "noise": 1, 
    "direction": "Flat", 
    "system_time": "2017-01-30T13:13:53-08:00", 
    "sgv": 81, 
    "dateString": "2017-01-30T06:22:32-08:00", 
    "device": "openaps://indy-ex2/cgm", 
    "unfiltered": 93408, 
    "rssi": 187, 
    "date": 1485786152000.0, 
    "filtered": 93984, 
    "type": "sgv", 
    "glucose": 81
  }, 
  {
    "trend_arrow": "FLAT", 
    "display_time": "2017-01-30T06:17:32-08:00", 
    "noise": 1, 
    "direction": "Flat", 
    "system_time": "2017-01-30T13:08:53-08:00", 
    "sgv": 80, 
    "dateString": "2017-01-30T06:17:32-08:00", 
    "device": "openaps://indy-ex2/cgm", 
    "unfiltered": 93104, 
    "rssi": 194, 
    "date": 1485785852000.0, 
    "filtered": 95536, 
    "type": "sgv", 
    "glucose": 80
  }, 
  {
    "trend_arrow": "FLAT", 
    "display_time": "2017-01-30T06:12:32-08:00", 
    "noise": 1, 
    "direction": "Flat", 
    "system_time": "2017-01-30T13:03:53-08:00", 
    "sgv": 82, 
    "dateString": "2017-01-30T06:12:32-08:00", 
    "device": "openaps://indy-ex2/cgm", 
    "unfiltered": 94544, 
    "rssi": 194, 
    "date": 1485785552000.0, 
    "filtered": 97792, 
    "type": "sgv", 
    "glucose": 82
  }, 
  {
    "trend_arrow": "FLAT", 
    "display_time": "2017-01-30T06:07:32-08:00", 
    "noise": 1, 
    "direction": "Flat", 
    "system_time": "2017-01-30T12:58:53-08:00", 
    "sgv": 85, 
    "dateString": "2017-01-30T06:07:32-08:00", 
    "device": "openaps://indy-ex2/cgm", 
    "unfiltered": 96848, 
    "rssi": 194, 
    "date": 1485785252000.0, 
    "filtered": 100736, 
    "type": "sgv", 
    "glucose": 85
  }, 
  {
    "trend_arrow": "FLAT", 
    "display_time": "2017-01-30T06:02:32-08:00", 
    "noise": 1, 
    "direction": "Flat", 
    "system_time": "2017-01-30T12:53:53-08:00", 
    "sgv": 87, 
    "dateString": "2017-01-30T06:02:32-08:00", 
    "device": "openaps://indy-ex2/cgm", 
    "unfiltered": 99136, 
    "rssi": 194, 
    "date": 1485784952000.0, 
    "filtered": 104432, 
    "type": "sgv", 
    "glucose": 87
  }
]